airflow/__init__.py
airflow/airflow-kpo-extension.py
airlfow_mlops-0.0.1.dist-info/LICENSE
airlfow_mlops-0.0.1.dist-info/METADATA
airlfow_mlops-0.0.1.dist-info/WHEEL
airlfow_mlops-0.0.1.dist-info/top_level.txt
airlfow_mlops-0.0.1.dist-info/RECORD
