Metadata-Version: 2.1
Name: airlfow-mlops
Version: 0.0.1
Summary: Librerias para airflow.
Home-page: https://github.com/noheroes/mlops-models.git
Author: Ruben Porras
Author-email: eporrasz@emeal.nttdata.com
Requires-Python: >=3.8
License-File: LICENSE
